app_math/__init__.py
app_math/checker.py
app_math/cli.py
math_helper_app-0.2.2.dist-info/licenses/LICENSE
tests/__init__.py
tests/test_checker.py
math_helper_app-0.2.2.dist-info/METADATA
math_helper_app-0.2.2.dist-info/WHEEL
math_helper_app-0.2.2.dist-info/entry_points.txt
math_helper_app-0.2.2.dist-info/top_level.txt
math_helper_app-0.2.2.dist-info/RECORD
