Metadata-Version: 2.4
Name: math-helper-app
Version: 0.2.2
Summary: Package simple pour vérifier si un nombre est pair ou impair
Author: christellelou904
Author-email: christellelou4@gmail.com
Classifier: Programming Language :: Python :: 3
Classifier: Topic :: Utilities
Classifier: License :: OSI Approved :: MIT License
License-File: LICENSE
Dynamic: author
Dynamic: author-email
Dynamic: classifier
Dynamic: license-file
Dynamic: summary
